modelbench/__init__.py
modelbench/benchmarks.py
modelbench/hazards.py
modelbench/modelgauge_runner.py
modelbench/record.py
modelbench/run.py
modelbench/scoring.py
modelbench/standards.json
modelbench/static_site_generator.py
modelbench/templates/_provisional.html
modelbench/templates/_test_runs_legend.html
modelbench/templates/base.html
modelbench/templates/benchmark.html
modelbench/templates/benchmarks.html
modelbench/templates/content/general.toml
modelbench/templates/content/general_purpose_ai_chat_benchmark.toml
modelbench/templates/content/general_purpose_ai_chat_benchmark_v_1.toml
modelbench/templates/content/grades.toml
modelbench/templates/content/hazards.toml
modelbench/templates/content/suts.toml
modelbench/templates/content/tests/bbq.toml
modelbench/templates/content/tests/real_toxicity_prompts.toml
modelbench/templates/content/tests/safe-cae-benign.toml
modelbench/templates/content/tests/safe-cae.toml
modelbench/templates/content/tests/safe-cbr.toml
modelbench/templates/content/tests/safe-gra.toml
modelbench/templates/content/tests/safe-ssh-benign.toml
modelbench/templates/content/tests/safe-ssh.toml
modelbench/templates/content/tests/safe-ter-benign.toml
modelbench/templates/content/tests/safe-ter.toml
modelbench/templates/content/tests/simple_safety_tests.toml
modelbench/templates/content/tests/xstest.toml
modelbench/templates/content_mlc/general.toml
modelbench/templates/content_mlc/general_purpose_ai_chat_benchmark.toml
modelbench/templates/index.html
modelbench/templates/macros/benchmark_card.html
modelbench/templates/macros/breadcrumb.html
modelbench/templates/macros/interpret_safety_ratings.html
modelbench/templates/macros/sut_card.html
modelbench/templates/macros/test_runs.html
modelbench/templates/macros/use_hazards_limitations.html
modelbench/templates/static/images/ml_commons_logo.png
modelbench/templates/static/style.css
modelbench/templates/test_report.html
modelbench/uid.py
modelbench/utilities.py
modelbench-0.6.0.dist-info/LICENSE.md
modelbench-0.6.0.dist-info/METADATA
modelbench-0.6.0.dist-info/WHEEL
modelbench-0.6.0.dist-info/entry_points.txt
modelbench-0.6.0.dist-info/RECORD
