Metadata-Version: 2.1
Name: modelbench
Version: 0.6.0
Summary: Run benchmarks and generate reports measuring the behavior of many AI Systems.
Home-page: https://github.com/mlcommons/modelbench
License: Apache-2.0
Keywords: AI,GenAI,LLM,NLP,evaluate,measure,quality,testing,prompt,safety,compare,artificial,intelligence,Large,Language,Models
Author: MLCommons AI Safety
Author-email: ai-safety-engineering@mlcommons.org
Requires-Python: >=3.10,<3.13
Classifier: Development Status :: 4 - Beta
Classifier: Intended Audience :: Developers
Classifier: Intended Audience :: Information Technology
Classifier: Intended Audience :: Science/Research
Classifier: License :: OSI Approved :: Apache Software License
Classifier: Natural Language :: English
Classifier: Operating System :: OS Independent
Classifier: Programming Language :: Python :: 3
Classifier: Programming Language :: Python :: 3.10
Classifier: Programming Language :: Python :: 3.11
Classifier: Programming Language :: Python :: 3.12
Classifier: Topic :: Scientific/Engineering
Classifier: Topic :: Scientific/Engineering :: Artificial Intelligence
Classifier: Topic :: Software Development :: Libraries :: Python Modules
Classifier: Topic :: System :: Benchmark
Classifier: Typing :: Typed
Requires-Dist: casefy (>=0.1.7,<0.2.0)
Requires-Dist: click (>=8.1.7,<9.0.0)
Requires-Dist: jinja2 (>=3.1.3,<4.0.0)
Requires-Dist: jq (>=1.6.0,<2.0.0)
Requires-Dist: modelgauge (>=0.6.0)
Requires-Dist: pip (>=24.0,<25.0)
Requires-Dist: retry (>=0.9.2,<0.10.0)
Requires-Dist: scipy (>=1.12.0,<2.0.0)
Requires-Dist: tabulate (>=0.9.0,<0.10.0)
Requires-Dist: termcolor (>=2.4.0,<3.0.0)
Project-URL: Repository, https://github.com/mlcommons/modelbench
